ps/basic/Config.py
ps/basic/Patterns.py
ps/basic/State.py
ps/basic/__init__.py
ps/basic/daemon.py
ps/basic/fsm.py
ps/basic/get_graph.py
ps/basic/ps_shell_log.py
ps/basic/utils.py
ps.basic-1.2.19.dist-info/LICENSE.TXT
ps.basic-1.2.19.dist-info/METADATA
ps.basic-1.2.19.dist-info/WHEEL
ps.basic-1.2.19.dist-info/entry_points.txt
ps.basic-1.2.19.dist-info/top_level.txt
ps.basic-1.2.19.dist-info/RECORD
