Metadata-Version: 2.1
Name: ps.basic
Version: 1.2.19
Summary: Basic class used in PS environment
Home-page: https://bitbucket.org/drsetz/ps.basic
Author: Setz
Author-email: thomas@setz.de
License: "License :: OSI Approved :: GNU General Public License (GPL)
Keywords: PS
Platform: UNKNOWN
Classifier: Development Status :: 4 - Beta
Classifier: Intended Audience :: Developers
Classifier: Operating System :: MacOS
Classifier: Operating System :: POSIX
Classifier: Operating System :: Microsoft :: Windows
Classifier: Programming Language :: Python :: 3.9
Classifier: Topic :: Software Development
Classifier: Topic :: Utilities
License-File: LICENSE.TXT
Requires-Dist: docopt
Requires-Dist: pygraphviz
